autotime/__init__.py
autotime/_version.py
ipython_autotime-0.3.2.dist-info/LICENSE
ipython_autotime-0.3.2.dist-info/METADATA
ipython_autotime-0.3.2.dist-info/WHEEL
ipython_autotime-0.3.2.dist-info/top_level.txt
ipython_autotime-0.3.2.dist-info/RECORD
