Metadata-Version: 2.1
Name: ipython-autotime
Version: 0.3.2
Summary: Time everything in IPython
Home-page: https://github.com/cpcloud/ipython-autotime
Author: Phillip Cloud
Author-email: cpcloud@gmail.com
License: Apache
Classifier: Environment :: Console
Classifier: Intended Audience :: Developers
Classifier: Intended Audience :: Science/Research
Classifier: Intended Audience :: Education
Classifier: License :: OSI Approved :: Apache Software License
Classifier: Operating System :: OS Independent
Classifier: Programming Language :: Python
Classifier: Topic :: Scientific/Engineering
Classifier: Topic :: Utilities
License-File: LICENSE
Requires-Dist: ipython
Requires-Dist: monotonic ; python_version < "3.3"
